{
    "products":[
        {
            "productName":"Fantech Gaming Headset",
            "price":"$25",
            "manufacturer":"China",
            "category":"Headset",
            "productionDate":"08/01/2020"
        }, 
        {
            "productName":"Onikuma Gaming Headset",
            "price":"$20",
            "manufacturer":"Japan",
            "category":"Headset",
            "productionDate":"04/02/2020"
        }, 
        {
            "productName":"JBL Wireless Headset",
            "price":"$10",
            "manufacturer":"USA",
            "category":"Headset",
            "productionDate":"02/20/2019"
        }, 
        {
            "productName":"Toshiba Core i5",
            "price":"400$",
            "manufacturer":"Japan",
            "category":"Laptop/Desktop",
            "productionDate":"01/20/2020"
        }, 
        {
            "productName":"AMD Ryzen Desktop",
            "price":"$1000",
            "manufacturer": "USA",
            "category":"Laptop/Desktop",
            "productionDate":"05/20/2020"
        }, 
        {
            "productName":"Apple MacBook",
            "price":"$5000",
            "manufacturer":"USA",
            "category":"Laptop/Desktop",
            "productionDate":"02/20/2021"
        }, 
        {
            "productName":"Vivo V21",
            "price":"$400",
            "manufacturer": "Taiwan",
            "category":"Smartphone",
            "productionDate":"05/20/2021"
        },
        {
            "productName":"Samsung galaxy Flip",
            "price":"$600",
            "manufacturer":"Korea",
            "category":"Smartphone",
            "productionDate":"07/21/2022"
        }, 
        {
            "productName":"Iphone 13",
            "price":"$1000",
            "manufacturer": "USA",
            "category":"Smartphone",
            "productionDate":"12/25/2021"
        }, 
        {
            "productName":"Logitech",
            "price":"$15",
            "manufacturer":"New York",
            "category":"Mouse",
            "productionDate":"10/15/2019"
        }, 
        {
            "productName":"Asus",
            "price":"$20",
            "manufacturer":"Taiwan",
            "category":"Mouse",
            "productionDate":"04/10/2020"
        }, 
        {
            "productName":"Fantech Gaming Mouse",
            "price":"$10",
            "manufacturer": "China",
            "category":"Mouse",
            "productionDate":""
        }
    ]   
}